topology_gen/__init__.py
topology_gen/generate_top.py
topology_gen/preprocess_mol2.py
topology_genrator-3.0.dist-info/LICENSE.txt
topology_genrator-3.0.dist-info/METADATA
topology_genrator-3.0.dist-info/WHEEL
topology_genrator-3.0.dist-info/entry_points.txt
topology_genrator-3.0.dist-info/top_level.txt
topology_genrator-3.0.dist-info/RECORD
