Metadata-Version: 2.1
Name: topology-genrator
Version: 3.0
Summary: A package to preprocess ligand files and generate topology files for GROMACS.
Home-page: https://github.com//naeemsbb/ligand_processor
Author: Naeem Mahmood Ashraf and Arslan Hamdi
Author-email: naeem.sbb@pu.edu.pk
License: UNKNOWN
Platform: UNKNOWN
Classifier: Programming Language :: Python :: 3
Classifier: License :: OSI Approved :: MIT License
Classifier: Operating System :: OS Independent
License-File: LICENSE.txt
Requires-Dist: numpy
Requires-Dist: parmed
